django_gsuite_email/__init__.py
django_gsuite_email/apps.py
django_gsuite_email/backends.py
django_gsuite_email/tests.py
django_gsuite_email/utils.py
djau_gsuite_email-0.1.6.dist-info/LICENSE
djau_gsuite_email-0.1.6.dist-info/METADATA
djau_gsuite_email-0.1.6.dist-info/WHEEL
djau_gsuite_email-0.1.6.dist-info/top_level.txt
djau_gsuite_email-0.1.6.dist-info/RECORD
