Metadata-Version: 2.1
Name: djau-gsuite-email
Version: 0.1.6
Summary: Send emails via a GSuite Service-account.
Home-page: https://github.com/slicefox/django-gsuite-email
Author: slicefox
Author-email: adithya.webdev@gmail.com
License: MIT
Classifier: License :: OSI Approved :: MIT License
Classifier: Programming Language :: Python
Classifier: Programming Language :: Python :: 3
Classifier: Programming Language :: Python :: 3.6
Classifier: Programming Language :: Python :: Implementation :: CPython
Classifier: Programming Language :: Python :: Implementation :: PyPy
Requires-Python: >=3.0.0
License-File: LICENSE
Requires-Dist: google-api-python-client >=1.8.0
Requires-Dist: google-auth >=1.11.3
